{
    "@context": "http://iiif.io/api/presentation/2/context.json",
    "@id": "https://readux.io/iiif/v2/7c17c670-d723-4c41-b8fe-61ba56938604/list/7c17c670-d723-4c41-b8fe-61ba56938604_11194-P0085-I0000-P0000-BP.jpg",
    "@type": "sc:AnnotationList",
    "resources": [
        {
            "@context": "http://iiif.io/api/presentation/2/context.json",
            "@id": "8b5421a1-577f-43bc-8b5b-dd214610600c",
            "@type": "oa:Annotation",
            "motivation": "sc:painting",
            "annotatedBy": {
                "name": "OCR"
            },
            "resource": {
                "@type": "cnt:ContentAsText",
                "format": "text/html",
                "chars": "<span id='8b5421a1-577f-43bc-8b5b-dd214610600c' class='anno-8b5421a1-577f-43bc-8b5b-dd214610600c' data-letter-spacing='0.026338544548976207'>Baccalaureate</span>",
                "language": "en"
            },
            "on": {
                "full": "https://readux.io/iiif/v2/7c17c670-d723-4c41-b8fe-61ba56938604/canvas/7c17c670-d723-4c41-b8fe-61ba56938604_11194-P0085-I0000-P0000-BP.jpg",
                "@type": "oa:SpecificResource",
                "within": {
                    "@id": "https://readux.io/iiif/v2/7c17c670-d723-4c41-b8fe-61ba56938604/manifest",
                    "@type": "sc:Manifest"
                },
                "selector": {
                    "@type": "oa:FragmentSelector",
                    "value": "xywh=723,360,556,90",
                    "item": {
                        "@type": "oa:FragmentSelector"
                    }
                }
            },
            "stylesheet": {
                "type": "CssStylesheet",
                "value": ".anno-8b5421a1-577f-43bc-8b5b-dd214610600c: { height: 90px; width: 556px; font-size: 56.25px; letter-spacing: 14.64423076923077px;}"
            }
        },
        {
            "@context": "http://iiif.io/api/presentation/2/context.json",
            "@id": "f083c815-d2ca-475c-81df-a2d24329b1e0",
            "@type": "oa:Annotation",
            "motivation": "sc:painting",
            "annotatedBy": {
                "name": "OCR"
            },
            "resource": {
                "@type": "cnt:ContentAsText",
                "format": "text/html",
                "chars": "<span id='f083c815-d2ca-475c-81df-a2d24329b1e0' class='anno-f083c815-d2ca-475c-81df-a2d24329b1e0' data-letter-spacing='0.06131628787878788'>Sermon</span>",
                "language": "en"
            },
            "on": {
                "full": "https://readux.io/iiif/v2/7c17c670-d723-4c41-b8fe-61ba56938604/canvas/7c17c670-d723-4c41-b8fe-61ba56938604_11194-P0085-I0000-P0000-BP.jpg",
                "@type": "oa:SpecificResource",
                "within": {
                    "@id": "https://readux.io/iiif/v2/7c17c670-d723-4c41-b8fe-61ba56938604/manifest",
                    "@type": "sc:Manifest"
                },
                "selector": {
                    "@type": "oa:FragmentSelector",
                    "value": "xywh=1307,363,264,89",
                    "item": {
                        "@type": "oa:FragmentSelector"
                    }
                }
            },
            "stylesheet": {
                "type": "CssStylesheet",
                "value": ".anno-f083c815-d2ca-475c-81df-a2d24329b1e0: { height: 89px; width: 264px; font-size: 55.625px; letter-spacing: 16.1875px;}"
            }
        },
        {
            "@context": "http://iiif.io/api/presentation/2/context.json",
            "@id": "e568f25a-1578-4b01-a681-98392f11a781",
            "@type": "oa:Annotation",
            "motivation": "sc:painting",
            "annotatedBy": {
                "name": "OCR"
            },
            "resource": {
                "@type": "cnt:ContentAsText",
                "format": "text/html",
                "chars": "<span id='e568f25a-1578-4b01-a681-98392f11a781' class='anno-e568f25a-1578-4b01-a681-98392f11a781' data-letter-spacing='0.013002622377622376'>Miscellaneous</span>",
                "language": "en"
            },
            "on": {
                "full": "https://readux.io/iiif/v2/7c17c670-d723-4c41-b8fe-61ba56938604/canvas/7c17c670-d723-4c41-b8fe-61ba56938604_11194-P0085-I0000-P0000-BP.jpg",
                "@type": "oa:SpecificResource",
                "within": {
                    "@id": "https://readux.io/iiif/v2/7c17c670-d723-4c41-b8fe-61ba56938604/manifest",
                    "@type": "sc:Manifest"
                },
                "selector": {
                    "@type": "oa:FragmentSelector",
                    "value": "xywh=2542,768,704,144",
                    "item": {
                        "@type": "oa:FragmentSelector"
                    }
                }
            },
            "stylesheet": {
                "type": "CssStylesheet",
                "value": ".anno-e568f25a-1578-4b01-a681-98392f11a781: { height: 144px; width: 704px; font-size: 90.0px; letter-spacing: 9.153846153846153px;}"
            }
        },
        {
            "@context": "http://iiif.io/api/presentation/2/context.json",
            "@id": "5c2d2b51-2f2a-463c-b470-38a8c6012547",
            "@type": "oa:Annotation",
            "motivation": "sc:painting",
            "annotatedBy": {
                "name": "OCR"
            },
            "resource": {
                "@type": "cnt:ContentAsText",
                "format": "text/html",
                "chars": "<span id='5c2d2b51-2f2a-463c-b470-38a8c6012547' class='anno-5c2d2b51-2f2a-463c-b470-38a8c6012547' data-letter-spacing='0.07346491228070176'>A</span>",
                "language": "en"
            },
            "on": {
                "full": "https://readux.io/iiif/v2/7c17c670-d723-4c41-b8fe-61ba56938604/canvas/7c17c670-d723-4c41-b8fe-61ba56938604_11194-P0085-I0000-P0000-BP.jpg",
                "@type": "oa:SpecificResource",
                "within": {
                    "@id": "https://readux.io/iiif/v2/7c17c670-d723-4c41-b8fe-61ba56938604/manifest",
                    "@type": "sc:Manifest"
                },
                "selector": {
                    "@type": "oa:FragmentSelector",
                    "value": "xywh=2290,979,57,169",
                    "item": {
                        "@type": "oa:FragmentSelector"
                    }
                }
            },
            "stylesheet": {
                "type": "CssStylesheet",
                "value": ".anno-5c2d2b51-2f2a-463c-b470-38a8c6012547: { height: 169px; width: 57px; font-size: 105.625px; letter-spacing: 4.1875px;}"
            }
        },
        {
            "@context": "http://iiif.io/api/presentation/2/context.json",
            "@id": "b04d984a-3128-49df-80fa-6d5707c24761",
            "@type": "oa:Annotation",
            "motivation": "sc:painting",
            "annotatedBy": {
                "name": "OCR"
            },
            "resource": {
                "@type": "cnt:ContentAsText",
                "format": "text/html",
                "chars": "<span id='b04d984a-3128-49df-80fa-6d5707c24761' class='anno-b04d984a-3128-49df-80fa-6d5707c24761' data-letter-spacing='-0.02490421455938697'>little</span>",
                "language": "en"
            },
            "on": {
                "full": "https://readux.io/iiif/v2/7c17c670-d723-4c41-b8fe-61ba56938604/canvas/7c17c670-d723-4c41-b8fe-61ba56938604_11194-P0085-I0000-P0000-BP.jpg",
                "@type": "oa:SpecificResource",
                "within": {
                    "@id": "https://readux.io/iiif/v2/7c17c670-d723-4c41-b8fe-61ba56938604/manifest",
                    "@type": "sc:Manifest"
                },
                "selector": {
                    "@type": "oa:FragmentSelector",
                    "value": "xywh=2404,975,261,160",
                    "item": {
                        "@type": "oa:FragmentSelector"
                    }
                }
            },
            "stylesheet": {
                "type": "CssStylesheet",
                "value": ".anno-b04d984a-3128-49df-80fa-6d5707c24761: { height: 160px; width: 261px; font-size: 100.0px; letter-spacing: -6.5px;}"
            }
        },
        {
            "@context": "http://iiif.io/api/presentation/2/context.json",
            "@id": "f2d937b9-093f-4c46-a450-c4fb1a7b57f9",
            "@type": "oa:Annotation",
            "motivation": "sc:painting",
            "annotatedBy": {
                "name": "OCR"
            },
            "resource": {
                "@type": "cnt:ContentAsText",
                "format": "text/html",
                "chars": "<span id='f2d937b9-093f-4c46-a450-c4fb1a7b57f9' class='anno-f2d937b9-093f-4c46-a450-c4fb1a7b57f9' data-letter-spacing='-0.00014076576576576576'>health</span>",
                "language": "en"
            },
            "on": {
                "full": "https://readux.io/iiif/v2/7c17c670-d723-4c41-b8fe-61ba56938604/canvas/7c17c670-d723-4c41-b8fe-61ba56938604_11194-P0085-I0000-P0000-BP.jpg",
                "@type": "oa:SpecificResource",
                "within": {
                    "@id": "https://readux.io/iiif/v2/7c17c670-d723-4c41-b8fe-61ba56938604/manifest",
                    "@type": "sc:Manifest"
                },
                "selector": {
                    "@type": "oa:FragmentSelector",
                    "value": "xywh=2787,959,296,158",
                    "item": {
                        "@type": "oa:FragmentSelector"
                    }
                }
            },
            "stylesheet": {
                "type": "CssStylesheet",
                "value": ".anno-f2d937b9-093f-4c46-a450-c4fb1a7b57f9: { height: 158px; width: 296px; font-size: 98.75px; letter-spacing: -0.041666666666666664px;}"
            }
        },
        {
            "@context": "http://iiif.io/api/presentation/2/context.json",
            "@id": "163cf0c6-2946-494c-84ba-33504546ff7b",
            "@type": "oa:Annotation",
            "motivation": "sc:painting",
            "annotatedBy": {
                "name": "OCR"
            },
            "resource": {
                "@type": "cnt:ContentAsText",
                "format": "text/html",
                "chars": "<span id='163cf0c6-2946-494c-84ba-33504546ff7b' class='anno-163cf0c6-2946-494c-84ba-33504546ff7b' data-letter-spacing='-0.22819767441860464'>,</span>",
                "language": "en"
            },
            "on": {
                "full": "https://readux.io/iiif/v2/7c17c670-d723-4c41-b8fe-61ba56938604/canvas/7c17c670-d723-4c41-b8fe-61ba56938604_11194-P0085-I0000-P0000-BP.jpg",
                "@type": "oa:SpecificResource",
                "within": {
                    "@id": "https://readux.io/iiif/v2/7c17c670-d723-4c41-b8fe-61ba56938604/manifest",
                    "@type": "sc:Manifest"
                },
                "selector": {
                    "@type": "oa:FragmentSelector",
                    "value": "xywh=3117,945,43,169",
                    "item": {
                        "@type": "oa:FragmentSelector"
                    }
                }
            },
            "stylesheet": {
                "type": "CssStylesheet",
                "value": ".anno-163cf0c6-2946-494c-84ba-33504546ff7b: { height: 169px; width: 43px; font-size: 105.625px; letter-spacing: -9.8125px;}"
            }
        },
        {
            "@context": "http://iiif.io/api/presentation/2/context.json",
            "@id": "d87a72f4-9087-4f37-bcda-b9c038640f6c",
            "@type": "oa:Annotation",
            "motivation": "sc:painting",
            "annotatedBy": {
                "name": "OCR"
            },
            "resource": {
                "@type": "cnt:ContentAsText",
                "format": "text/html",
                "chars": "<span id='d87a72f4-9087-4f37-bcda-b9c038640f6c' class='anno-d87a72f4-9087-4f37-bcda-b9c038640f6c' data-letter-spacing='0.02925531914893617'>A</span>",
                "language": "en"
            },
            "on": {
                "full": "https://readux.io/iiif/v2/7c17c670-d723-4c41-b8fe-61ba56938604/canvas/7c17c670-d723-4c41-b8fe-61ba56938604_11194-P0085-I0000-P0000-BP.jpg",
                "@type": "oa:SpecificResource",
                "within": {
                    "@id": "https://readux.io/iiif/v2/7c17c670-d723-4c41-b8fe-61ba56938604/manifest",
                    "@type": "sc:Manifest"
                },
                "selector": {
                    "@type": "oa:FragmentSelector",
                    "value": "xywh=2278,1117,47,146",
                    "item": {
                        "@type": "oa:FragmentSelector"
                    }
                }
            },
            "stylesheet": {
                "type": "CssStylesheet",
                "value": ".anno-d87a72f4-9087-4f37-bcda-b9c038640f6c: { height: 146px; width: 47px; font-size: 91.25px; letter-spacing: 1.375px;}"
            }
        },
        {
            "@context": "http://iiif.io/api/presentation/2/context.json",
            "@id": "90545489-5b20-4c2a-bc65-8a833e166431",
            "@type": "oa:Annotation",
            "motivation": "sc:painting",
            "annotatedBy": {
                "name": "OCR"
            },
            "resource": {
                "@type": "cnt:ContentAsText",
                "format": "text/html",
                "chars": "<span id='90545489-5b20-4c2a-bc65-8a833e166431' class='anno-90545489-5b20-4c2a-bc65-8a833e166431' data-letter-spacing='-0.0029069767441860465'>little</span>",
                "language": "en"
            },
            "on": {
                "full": "https://readux.io/iiif/v2/7c17c670-d723-4c41-b8fe-61ba56938604/canvas/7c17c670-d723-4c41-b8fe-61ba56938604_11194-P0085-I0000-P0000-BP.jpg",
                "@type": "oa:SpecificResource",
                "within": {
                    "@id": "https://readux.io/iiif/v2/7c17c670-d723-4c41-b8fe-61ba56938604/manifest",
                    "@type": "sc:Manifest"
                },
                "selector": {
                    "@type": "oa:FragmentSelector",
                    "value": "xywh=2418,1113,258,140",
                    "item": {
                        "@type": "oa:FragmentSelector"
                    }
                }
            },
            "stylesheet": {
                "type": "CssStylesheet",
                "value": ".anno-90545489-5b20-4c2a-bc65-8a833e166431: { height: 140px; width: 258px; font-size: 87.5px; letter-spacing: -0.75px;}"
            }
        },
        {
            "@context": "http://iiif.io/api/presentation/2/context.json",
            "@id": "ae66bda4-f9cf-44bf-ad3b-276dd2cc89af",
            "@type": "oa:Annotation",
            "motivation": "sc:painting",
            "annotatedBy": {
                "name": "OCR"
            },
            "resource": {
                "@type": "cnt:ContentAsText",
                "format": "text/html",
                "chars": "<span id='ae66bda4-f9cf-44bf-ad3b-276dd2cc89af' class='anno-ae66bda4-f9cf-44bf-ad3b-276dd2cc89af' data-letter-spacing='0.059613769941225865'>wealth</span>",
                "language": "en"
            },
            "on": {
                "full": "https://readux.io/iiif/v2/7c17c670-d723-4c41-b8fe-61ba56938604/canvas/7c17c670-d723-4c41-b8fe-61ba56938604_11194-P0085-I0000-P0000-BP.jpg",
                "@type": "oa:SpecificResource",
                "within": {
                    "@id": "https://readux.io/iiif/v2/7c17c670-d723-4c41-b8fe-61ba56938604/manifest",
                    "@type": "sc:Manifest"
                },
                "selector": {
                    "@type": "oa:FragmentSelector",
                    "value": "xywh=2728,1104,397,136",
                    "item": {
                        "@type": "oa:FragmentSelector"
                    }
                }
            },
            "stylesheet": {
                "type": "CssStylesheet",
                "value": ".anno-ae66bda4-f9cf-44bf-ad3b-276dd2cc89af: { height: 136px; width: 397px; font-size: 85.0px; letter-spacing: 23.666666666666668px;}"
            }
        },
        {
            "@context": "http://iiif.io/api/presentation/2/context.json",
            "@id": "e2ba163d-56a2-42ed-91ba-521f53aa94bb",
            "@type": "oa:Annotation",
            "motivation": "sc:painting",
            "annotatedBy": {
                "name": "OCR"
            },
            "resource": {
                "@type": "cnt:ContentAsText",
                "format": "text/html",
                "chars": "<span id='e2ba163d-56a2-42ed-91ba-521f53aa94bb' class='anno-e2ba163d-56a2-42ed-91ba-521f53aa94bb' data-letter-spacing='-0.03587962962962963'>A</span>",
                "language": "en"
            },
            "on": {
                "full": "https://readux.io/iiif/v2/7c17c670-d723-4c41-b8fe-61ba56938604/canvas/7c17c670-d723-4c41-b8fe-61ba56938604_11194-P0085-I0000-P0000-BP.jpg",
                "@type": "oa:SpecificResource",
                "within": {
                    "@id": "https://readux.io/iiif/v2/7c17c670-d723-4c41-b8fe-61ba56938604/manifest",
                    "@type": "sc:Manifest"
                },
                "selector": {
                    "@type": "oa:FragmentSelector",
                    "value": "xywh=2279,1243,54,179",
                    "item": {
                        "@type": "oa:FragmentSelector"
                    }
                }
            },
            "stylesheet": {
                "type": "CssStylesheet",
                "value": ".anno-e2ba163d-56a2-42ed-91ba-521f53aa94bb: { height: 179px; width: 54px; font-size: 111.875px; letter-spacing: -1.9375px;}"
            }
        },
        {
            "@context": "http://iiif.io/api/presentation/2/context.json",
            "@id": "24ec0dcc-aa20-4928-ab07-b8c13287c326",
            "@type": "oa:Annotation",
            "motivation": "sc:painting",
            "annotatedBy": {
                "name": "OCR"
            },
            "resource": {
                "@type": "cnt:ContentAsText",
                "format": "text/html",
                "chars": "<span id='24ec0dcc-aa20-4928-ab07-b8c13287c326' class='anno-24ec0dcc-aa20-4928-ab07-b8c13287c326' data-letter-spacing='-0.056726907630522086'>little</span>",
                "language": "en"
            },
            "on": {
                "full": "https://readux.io/iiif/v2/7c17c670-d723-4c41-b8fe-61ba56938604/canvas/7c17c670-d723-4c41-b8fe-61ba56938604_11194-P0085-I0000-P0000-BP.jpg",
                "@type": "oa:SpecificResource",
                "within": {
                    "@id": "https://readux.io/iiif/v2/7c17c670-d723-4c41-b8fe-61ba56938604/manifest",
                    "@type": "sc:Manifest"
                },
                "selector": {
                    "@type": "oa:FragmentSelector",
                    "value": "xywh=2379,1242,249,178",
                    "item": {
                        "@type": "oa:FragmentSelector"
                    }
                }
            },
            "stylesheet": {
                "type": "CssStylesheet",
                "value": ".anno-24ec0dcc-aa20-4928-ab07-b8c13287c326: { height: 178px; width: 249px; font-size: 111.25px; letter-spacing: -14.125px;}"
            }
        },
        {
            "@context": "http://iiif.io/api/presentation/2/context.json",
            "@id": "3e5b708d-1efc-4da6-a164-377957313a44",
            "@type": "oa:Annotation",
            "motivation": "sc:painting",
            "annotatedBy": {
                "name": "OCR"
            },
            "resource": {
                "@type": "cnt:ContentAsText",
                "format": "text/html",
                "chars": "<span id='3e5b708d-1efc-4da6-a164-377957313a44' class='anno-3e5b708d-1efc-4da6-a164-377957313a44' data-letter-spacing='-0.09984276729559749'>life</span>",
                "language": "en"
            },
            "on": {
                "full": "https://readux.io/iiif/v2/7c17c670-d723-4c41-b8fe-61ba56938604/canvas/7c17c670-d723-4c41-b8fe-61ba56938604_11194-P0085-I0000-P0000-BP.jpg",
                "@type": "oa:SpecificResource",
                "within": {
                    "@id": "https://readux.io/iiif/v2/7c17c670-d723-4c41-b8fe-61ba56938604/manifest",
                    "@type": "sc:Manifest"
                },
                "selector": {
                    "@type": "oa:FragmentSelector",
                    "value": "xywh=2728,1240,159,178",
                    "item": {
                        "@type": "oa:FragmentSelector"
                    }
                }
            },
            "stylesheet": {
                "type": "CssStylesheet",
                "value": ".anno-3e5b708d-1efc-4da6-a164-377957313a44: { height: 178px; width: 159px; font-size: 111.25px; letter-spacing: -15.875px;}"
            }
        },
        {
            "@context": "http://iiif.io/api/presentation/2/context.json",
            "@id": "6124e0e9-3794-45c3-bf63-2f68d92af6ad",
            "@type": "oa:Annotation",
            "motivation": "sc:painting",
            "annotatedBy": {
                "name": "OCR"
            },
            "resource": {
                "@type": "cnt:ContentAsText",
                "format": "text/html",
                "chars": "<span id='6124e0e9-3794-45c3-bf63-2f68d92af6ad' class='anno-6124e0e9-3794-45c3-bf63-2f68d92af6ad' data-letter-spacing='-0.029897186147186148'>and</span>",
                "language": "en"
            },
            "on": {
                "full": "https://readux.io/iiif/v2/7c17c670-d723-4c41-b8fe-61ba56938604/canvas/7c17c670-d723-4c41-b8fe-61ba56938604_11194-P0085-I0000-P0000-BP.jpg",
                "@type": "oa:SpecificResource",
                "within": {
                    "@id": "https://readux.io/iiif/v2/7c17c670-d723-4c41-b8fe-61ba56938604/manifest",
                    "@type": "sc:Manifest"
                },
                "selector": {
                    "@type": "oa:FragmentSelector",
                    "value": "xywh=2913,1238,154,179",
                    "item": {
                        "@type": "oa:FragmentSelector"
                    }
                }
            },
            "stylesheet": {
                "type": "CssStylesheet",
                "value": ".anno-6124e0e9-3794-45c3-bf63-2f68d92af6ad: { height: 179px; width: 154px; font-size: 111.875px; letter-spacing: -4.604166666666667px;}"
            }
        },
        {
            "@context": "http://iiif.io/api/presentation/2/context.json",
            "@id": "eed831b3-fe20-47af-94a8-da894ee4682c",
            "@type": "oa:Annotation",
            "motivation": "sc:painting",
            "annotatedBy": {
                "name": "OCR"
            },
            "resource": {
                "@type": "cnt:ContentAsText",
                "format": "text/html",
                "chars": "<span id='eed831b3-fe20-47af-94a8-da894ee4682c' class='anno-eed831b3-fe20-47af-94a8-da894ee4682c' data-letter-spacing='-0.013190954773869347'>freedond</span>",
                "language": "en"
            },
            "on": {
                "full": "https://readux.io/iiif/v2/7c17c670-d723-4c41-b8fe-61ba56938604/canvas/7c17c670-d723-4c41-b8fe-61ba56938604_11194-P0085-I0000-P0000-BP.jpg",
                "@type": "oa:SpecificResource",
                "within": {
                    "@id": "https://readux.io/iiif/v2/7c17c670-d723-4c41-b8fe-61ba56938604/manifest",
                    "@type": "sc:Manifest"
                },
                "selector": {
                    "@type": "oa:FragmentSelector",
                    "value": "xywh=3172,1237,398,176",
                    "item": {
                        "@type": "oa:FragmentSelector"
                    }
                }
            },
            "stylesheet": {
                "type": "CssStylesheet",
                "value": ".anno-eed831b3-fe20-47af-94a8-da894ee4682c: { height: 176px; width: 398px; font-size: 110.0px; letter-spacing: -5.25px;}"
            }
        },
        {
            "@context": "http://iiif.io/api/presentation/2/context.json",
            "@id": "29435e2c-585f-4a4b-b56b-41f645a4d3a8",
            "@type": "oa:Annotation",
            "motivation": "sc:painting",
            "annotatedBy": {
                "name": "OCR"
            },
            "resource": {
                "@type": "cnt:ContentAsText",
                "format": "text/html",
                "chars": "<span id='29435e2c-585f-4a4b-b56b-41f645a4d3a8' class='anno-29435e2c-585f-4a4b-b56b-41f645a4d3a8' data-letter-spacing='0.023936170212765957'>Same</span>",
                "language": "en"
            },
            "on": {
                "full": "https://readux.io/iiif/v2/7c17c670-d723-4c41-b8fe-61ba56938604/canvas/7c17c670-d723-4c41-b8fe-61ba56938604_11194-P0085-I0000-P0000-BP.jpg",
                "@type": "oa:SpecificResource",
                "within": {
                    "@id": "https://readux.io/iiif/v2/7c17c670-d723-4c41-b8fe-61ba56938604/manifest",
                    "@type": "sc:Manifest"
                },
                "selector": {
                    "@type": "oa:FragmentSelector",
                    "value": "xywh=2329,1383,235,170",
                    "item": {
                        "@type": "oa:FragmentSelector"
                    }
                }
            },
            "stylesheet": {
                "type": "CssStylesheet",
                "value": ".anno-29435e2c-585f-4a4b-b56b-41f645a4d3a8: { height: 170px; width: 235px; font-size: 106.25px; letter-spacing: 5.625px;}"
            }
        },
        {
            "@context": "http://iiif.io/api/presentation/2/context.json",
            "@id": "bb98c947-d1ac-4973-8643-8e0686c984e1",
            "@type": "oa:Annotation",
            "motivation": "sc:painting",
            "annotatedBy": {
                "name": "OCR"
            },
            "resource": {
                "@type": "cnt:ContentAsText",
                "format": "text/html",
                "chars": "<span id='bb98c947-d1ac-4973-8643-8e0686c984e1' class='anno-bb98c947-d1ac-4973-8643-8e0686c984e1' data-letter-spacing='-0.15773809523809526'>fen</span>",
                "language": "en"
            },
            "on": {
                "full": "https://readux.io/iiif/v2/7c17c670-d723-4c41-b8fe-61ba56938604/canvas/7c17c670-d723-4c41-b8fe-61ba56938604_11194-P0085-I0000-P0000-BP.jpg",
                "@type": "oa:SpecificResource",
                "within": {
                    "@id": "https://readux.io/iiif/v2/7c17c670-d723-4c41-b8fe-61ba56938604/manifest",
                    "@type": "sc:Manifest"
                },
                "selector": {
                    "@type": "oa:FragmentSelector",
                    "value": "xywh=2661,1370,112,176",
                    "item": {
                        "@type": "oa:FragmentSelector"
                    }
                }
            },
            "stylesheet": {
                "type": "CssStylesheet",
                "value": ".anno-bb98c947-d1ac-4973-8643-8e0686c984e1: { height: 176px; width: 112px; font-size: 110.0px; letter-spacing: -17.666666666666668px;}"
            }
        },
        {
            "@context": "http://iiif.io/api/presentation/2/context.json",
            "@id": "482d425f-732a-4248-9634-21907123067c",
            "@type": "oa:Annotation",
            "motivation": "sc:painting",
            "annotatedBy": {
                "name": "OCR"
            },
            "resource": {
                "@type": "cnt:ContentAsText",
                "format": "text/html",
                "chars": "<span id='482d425f-732a-4248-9634-21907123067c' class='anno-482d425f-732a-4248-9634-21907123067c' data-letter-spacing='0.03854166666666667'>fiende</span>",
                "language": "en"
            },
            "on": {
                "full": "https://readux.io/iiif/v2/7c17c670-d723-4c41-b8fe-61ba56938604/canvas/7c17c670-d723-4c41-b8fe-61ba56938604_11194-P0085-I0000-P0000-BP.jpg",
                "@type": "oa:SpecificResource",
                "within": {
                    "@id": "https://readux.io/iiif/v2/7c17c670-d723-4c41-b8fe-61ba56938604/manifest",
                    "@type": "sc:Manifest"
                },
                "selector": {
                    "@type": "oa:FragmentSelector",
                    "value": "xywh=2889,1362,400,164",
                    "item": {
                        "@type": "oa:FragmentSelector"
                    }
                }
            },
            "stylesheet": {
                "type": "CssStylesheet",
                "value": ".anno-482d425f-732a-4248-9634-21907123067c: { height: 164px; width: 400px; font-size: 102.5px; letter-spacing: 15.416666666666666px;}"
            }
        },
        {
            "@context": "http://iiif.io/api/presentation/2/context.json",
            "@id": "1c6732df-33e6-4d65-9ce9-7dbd13cfef91",
            "@type": "oa:Annotation",
            "motivation": "sc:painting",
            "annotatedBy": {
                "name": "OCR"
            },
            "resource": {
                "@type": "cnt:ContentAsText",
                "format": "text/html",
                "chars": "<span id='1c6732df-33e6-4d65-9ce9-7dbd13cfef91' class='anno-1c6732df-33e6-4d65-9ce9-7dbd13cfef91' data-letter-spacing='0.04675582354153783'>Facentand</span>",
                "language": "en"
            },
            "on": {
                "full": "https://readux.io/iiif/v2/7c17c670-d723-4c41-b8fe-61ba56938604/canvas/7c17c670-d723-4c41-b8fe-61ba56938604_11194-P0085-I0000-P0000-BP.jpg",
                "@type": "oa:SpecificResource",
                "within": {
                    "@id": "https://readux.io/iiif/v2/7c17c670-d723-4c41-b8fe-61ba56938604/manifest",
                    "@type": "sc:Manifest"
                },
                "selector": {
                    "@type": "oa:FragmentSelector",
                    "value": "xywh=2324,1518,539,111",
                    "item": {
                        "@type": "oa:FragmentSelector"
                    }
                }
            },
            "stylesheet": {
                "type": "CssStylesheet",
                "value": ".anno-1c6732df-33e6-4d65-9ce9-7dbd13cfef91: { height: 111px; width: 539px; font-size: 69.375px; letter-spacing: 25.20138888888889px;}"
            }
        },
        {
            "@context": "http://iiif.io/api/presentation/2/context.json",
            "@id": "7c88b3fb-b328-4009-ad87-cd64fabf5f88",
            "@type": "oa:Annotation",
            "motivation": "sc:painting",
            "annotatedBy": {
                "name": "OCR"
            },
            "resource": {
                "@type": "cnt:ContentAsText",
                "format": "text/html",
                "chars": "<span id='7c88b3fb-b328-4009-ad87-cd64fabf5f88' class='anno-7c88b3fb-b328-4009-ad87-cd64fabf5f88' data-letter-spacing='0.07222222222222222'>ends</span>",
                "language": "en"
            },
            "on": {
                "full": "https://readux.io/iiif/v2/7c17c670-d723-4c41-b8fe-61ba56938604/canvas/7c17c670-d723-4c41-b8fe-61ba56938604_11194-P0085-I0000-P0000-BP.jpg",
                "@type": "oa:SpecificResource",
                "within": {
                    "@id": "https://readux.io/iiif/v2/7c17c670-d723-4c41-b8fe-61ba56938604/manifest",
                    "@type": "sc:Manifest"
                },
                "selector": {
                    "@type": "oa:FragmentSelector",
                    "value": "xywh=2995,1483,225,128",
                    "item": {
                        "@type": "oa:FragmentSelector"
                    }
                }
            },
            "stylesheet": {
                "type": "CssStylesheet",
                "value": ".anno-7c88b3fb-b328-4009-ad87-cd64fabf5f88: { height: 128px; width: 225px; font-size: 80.0px; letter-spacing: 16.25px;}"
            }
        },
        {
            "@context": "http://iiif.io/api/presentation/2/context.json",
            "@id": "6b5f2cd9-8802-46e6-9f33-1bac5df5da2f",
            "@type": "oa:Annotation",
            "motivation": "sc:painting",
            "annotatedBy": {
                "name": "OCR"
            },
            "resource": {
                "@type": "cnt:ContentAsText",
                "format": "text/html",
                "chars": "<span id='6b5f2cd9-8802-46e6-9f33-1bac5df5da2f' class='anno-6b5f2cd9-8802-46e6-9f33-1bac5df5da2f' data-letter-spacing='0.07317323481116585'>But</span>",
                "language": "en"
            },
            "on": {
                "full": "https://readux.io/iiif/v2/7c17c670-d723-4c41-b8fe-61ba56938604/canvas/7c17c670-d723-4c41-b8fe-61ba56938604_11194-P0085-I0000-P0000-BP.jpg",
                "@type": "oa:SpecificResource",
                "within": {
                    "@id": "https://readux.io/iiif/v2/7c17c670-d723-4c41-b8fe-61ba56938604/manifest",
                    "@type": "sc:Manifest"
                },
                "selector": {
                    "@type": "oa:FragmentSelector",
                    "value": "xywh=2259,1602,203,169",
                    "item": {
                        "@type": "oa:FragmentSelector"
                    }
                }
            },
            "stylesheet": {
                "type": "CssStylesheet",
                "value": ".anno-6b5f2cd9-8802-46e6-9f33-1bac5df5da2f: { height: 169px; width: 203px; font-size: 105.625px; letter-spacing: 14.854166666666666px;}"
            }
        },
        {
            "@context": "http://iiif.io/api/presentation/2/context.json",
            "@id": "3458e148-ec8a-47f4-8f86-52082a35d67c",
            "@type": "oa:Annotation",
            "motivation": "sc:painting",
            "annotatedBy": {
                "name": "OCR"
            },
            "resource": {
                "@type": "cnt:ContentAsText",
                "format": "text/html",
                "chars": "<span id='3458e148-ec8a-47f4-8f86-52082a35d67c' class='anno-3458e148-ec8a-47f4-8f86-52082a35d67c' data-letter-spacing='0.022727272727272728'>a</span>",
                "language": "en"
            },
            "on": {
                "full": "https://readux.io/iiif/v2/7c17c670-d723-4c41-b8fe-61ba56938604/canvas/7c17c670-d723-4c41-b8fe-61ba56938604_11194-P0085-I0000-P0000-BP.jpg",
                "@type": "oa:SpecificResource",
                "within": {
                    "@id": "https://readux.io/iiif/v2/7c17c670-d723-4c41-b8fe-61ba56938604/manifest",
                    "@type": "sc:Manifest"
                },
                "selector": {
                    "@type": "oa:FragmentSelector",
                    "value": "xywh=2490,1597,55,172",
                    "item": {
                        "@type": "oa:FragmentSelector"
                    }
                }
            },
            "stylesheet": {
                "type": "CssStylesheet",
                "value": ".anno-3458e148-ec8a-47f4-8f86-52082a35d67c: { height: 172px; width: 55px; font-size: 107.5px; letter-spacing: 1.25px;}"
            }
        },
        {
            "@context": "http://iiif.io/api/presentation/2/context.json",
            "@id": "cf258618-aaf0-4e5f-b2c5-f7c9bdc72673",
            "@type": "oa:Annotation",
            "motivation": "sc:painting",
            "annotatedBy": {
                "name": "OCR"
            },
            "resource": {
                "@type": "cnt:ContentAsText",
                "format": "text/html",
                "chars": "<span id='cf258618-aaf0-4e5f-b2c5-f7c9bdc72673' class='anno-cf258618-aaf0-4e5f-b2c5-f7c9bdc72673' data-letter-spacing='-0.03328544061302682'>little</span>",
                "language": "en"
            },
            "on": {
                "full": "https://readux.io/iiif/v2/7c17c670-d723-4c41-b8fe-61ba56938604/canvas/7c17c670-d723-4c41-b8fe-61ba56938604_11194-P0085-I0000-P0000-BP.jpg",
                "@type": "oa:SpecificResource",
                "within": {
                    "@id": "https://readux.io/iiif/v2/7c17c670-d723-4c41-b8fe-61ba56938604/manifest",
                    "@type": "sc:Manifest"
                },
                "selector": {
                    "@type": "oa:FragmentSelector",
                    "value": "xywh=2638,1593,261,167",
                    "item": {
                        "@type": "oa:FragmentSelector"
                    }
                }
            },
            "stylesheet": {
                "type": "CssStylesheet",
                "value": ".anno-cf258618-aaf0-4e5f-b2c5-f7c9bdc72673: { height: 167px; width: 261px; font-size: 104.375px; letter-spacing: -8.6875px;}"
            }
        },
        {
            "@context": "http://iiif.io/api/presentation/2/context.json",
            "@id": "65f3035e-1e33-4a7c-a79a-3ecebc4dd669",
            "@type": "oa:Annotation",
            "motivation": "sc:painting",
            "annotatedBy": {
                "name": "OCR"
            },
            "resource": {
                "@type": "cnt:ContentAsText",
                "format": "text/html",
                "chars": "<span id='65f3035e-1e33-4a7c-a79a-3ecebc4dd669' class='anno-65f3035e-1e33-4a7c-a79a-3ecebc4dd669' data-letter-spacing='-0.010433467741935484'>cause</span>",
                "language": "en"
            },
            "on": {
                "full": "https://readux.io/iiif/v2/7c17c670-d723-4c41-b8fe-61ba56938604/canvas/7c17c670-d723-4c41-b8fe-61ba56938604_11194-P0085-I0000-P0000-BP.jpg",
                "@type": "oa:SpecificResource",
                "within": {
                    "@id": "https://readux.io/iiif/v2/7c17c670-d723-4c41-b8fe-61ba56938604/manifest",
                    "@type": "sc:Manifest"
                },
                "selector": {
                    "@type": "oa:FragmentSelector",
                    "value": "xywh=2929,1587,248,167",
                    "item": {
                        "@type": "oa:FragmentSelector"
                    }
                }
            },
            "stylesheet": {
                "type": "CssStylesheet",
                "value": ".anno-65f3035e-1e33-4a7c-a79a-3ecebc4dd669: { height: 167px; width: 248px; font-size: 104.375px; letter-spacing: -2.5875px;}"
            }
        },
        {
            "@context": "http://iiif.io/api/presentation/2/context.json",
            "@id": "f443e863-47a7-497a-af5f-5977f67a30f6",
            "@type": "oa:Annotation",
            "motivation": "sc:painting",
            "annotatedBy": {
                "name": "OCR"
            },
            "resource": {
                "@type": "cnt:ContentAsText",
                "format": "text/html",
                "chars": "<span id='f443e863-47a7-497a-af5f-5977f67a30f6' class='anno-f443e863-47a7-497a-af5f-5977f67a30f6' data-letter-spacing='-0.034375'>to</span>",
                "language": "en"
            },
            "on": {
                "full": "https://readux.io/iiif/v2/7c17c670-d723-4c41-b8fe-61ba56938604/canvas/7c17c670-d723-4c41-b8fe-61ba56938604_11194-P0085-I0000-P0000-BP.jpg",
                "@type": "oa:SpecificResource",
                "within": {
                    "@id": "https://readux.io/iiif/v2/7c17c670-d723-4c41-b8fe-61ba56938604/manifest",
                    "@type": "sc:Manifest"
                },
                "selector": {
                    "@type": "oa:FragmentSelector",
                    "value": "xywh=3242,1580,100,171",
                    "item": {
                        "@type": "oa:FragmentSelector"
                    }
                }
            },
            "stylesheet": {
                "type": "CssStylesheet",
                "value": ".anno-f443e863-47a7-497a-af5f-5977f67a30f6: { height: 171px; width: 100px; font-size: 106.875px; letter-spacing: -3.4375px;}"
            }
        },
        {
            "@context": "http://iiif.io/api/presentation/2/context.json",
            "@id": "ea1bb1ba-41c1-4e8a-a281-18b46775fa65",
            "@type": "oa:Annotation",
            "motivation": "sc:painting",
            "annotatedBy": {
                "name": "OCR"
            },
            "resource": {
                "@type": "cnt:ContentAsText",
                "format": "text/html",
                "chars": "<span id='ea1bb1ba-41c1-4e8a-a281-18b46775fa65' class='anno-ea1bb1ba-41c1-4e8a-a281-18b46775fa65' data-letter-spacing='0.039495450785773364'>needen</span>",
                "language": "en"
            },
            "on": {
                "full": "https://readux.io/iiif/v2/7c17c670-d723-4c41-b8fe-61ba56938604/canvas/7c17c670-d723-4c41-b8fe-61ba56938604_11194-P0085-I0000-P0000-BP.jpg",
                "@type": "oa:SpecificResource",
                "within": {
                    "@id": "https://readux.io/iiif/v2/7c17c670-d723-4c41-b8fe-61ba56938604/manifest",
                    "@type": "sc:Manifest"
                },
                "selector": {
                    "@type": "oa:FragmentSelector",
                    "value": "xywh=3381,1577,403,164",
                    "item": {
                        "@type": "oa:FragmentSelector"
                    }
                }
            },
            "stylesheet": {
                "type": "CssStylesheet",
                "value": ".anno-ea1bb1ba-41c1-4e8a-a281-18b46775fa65: { height: 164px; width: 403px; font-size: 102.5px; letter-spacing: 15.916666666666666px;}"
            }
        },
        {
            "@context": "http://iiif.io/api/presentation/2/context.json",
            "@id": "38cc12f8-80d2-4908-9e69-87835fac2d9f",
            "@type": "oa:Annotation",
            "motivation": "sc:painting",
            "annotatedBy": {
                "name": "OCR"
            },
            "resource": {
                "@type": "cnt:ContentAsText",
                "format": "text/html",
                "chars": "<span id='38cc12f8-80d2-4908-9e69-87835fac2d9f' class='anno-38cc12f8-80d2-4908-9e69-87835fac2d9f' data-letter-spacing='-0.4144736842105263'>.</span>",
                "language": "en"
            },
            "on": {
                "full": "https://readux.io/iiif/v2/7c17c670-d723-4c41-b8fe-61ba56938604/canvas/7c17c670-d723-4c41-b8fe-61ba56938604_11194-P0085-I0000-P0000-BP.jpg",
                "@type": "oa:SpecificResource",
                "within": {
                    "@id": "https://readux.io/iiif/v2/7c17c670-d723-4c41-b8fe-61ba56938604/manifest",
                    "@type": "sc:Manifest"
                },
                "selector": {
                    "@type": "oa:FragmentSelector",
                    "value": "xywh=3828,1566,38,172",
                    "item": {
                        "@type": "oa:FragmentSelector"
                    }
                }
            },
            "stylesheet": {
                "type": "CssStylesheet",
                "value": ".anno-38cc12f8-80d2-4908-9e69-87835fac2d9f: { height: 172px; width: 38px; font-size: 107.5px; letter-spacing: -15.75px;}"
            }
        },
        {
            "@context": "http://iiif.io/api/presentation/2/context.json",
            "@id": "40c70169-14aa-404f-b613-df923b0f7f8d",
            "@type": "oa:Annotation",
            "motivation": "sc:painting",
            "annotatedBy": {
                "name": "OCR"
            },
            "resource": {
                "@type": "cnt:ContentAsText",
                "format": "text/html",
                "chars": "<span id='40c70169-14aa-404f-b613-df923b0f7f8d' class='anno-40c70169-14aa-404f-b613-df923b0f7f8d' data-letter-spacing='0.13286163522012578'>168</span>",
                "language": "en"
            },
            "on": {
                "full": "https://readux.io/iiif/v2/7c17c670-d723-4c41-b8fe-61ba56938604/canvas/7c17c670-d723-4c41-b8fe-61ba56938604_11194-P0085-I0000-P0000-BP.jpg",
                "@type": "oa:SpecificResource",
                "within": {
                    "@id": "https://readux.io/iiif/v2/7c17c670-d723-4c41-b8fe-61ba56938604/manifest",
                    "@type": "sc:Manifest"
                },
                "selector": {
                    "@type": "oa:FragmentSelector",
                    "value": "xywh=1131,2820,53,34",
                    "item": {
                        "@type": "oa:FragmentSelector"
                    }
                }
            },
            "stylesheet": {
                "type": "CssStylesheet",
                "value": ".anno-40c70169-14aa-404f-b613-df923b0f7f8d: { height: 34px; width: 53px; font-size: 21.25px; letter-spacing: 7.041666666666667px;}"
            }
        },
        {
            "@context": "http://iiif.io/api/presentation/2/context.json",
            "@id": "e033742b-97d4-4915-bf29-61dbf6199af8",
            "@type": "oa:Annotation",
            "motivation": "sc:painting",
            "annotatedBy": {
                "name": "OCR"
            },
            "resource": {
                "@type": "cnt:ContentAsText",
                "format": "text/html",
                "chars": "<span id='e033742b-97d4-4915-bf29-61dbf6199af8' class='anno-e033742b-97d4-4915-bf29-61dbf6199af8' data-letter-spacing='0.16091954022988506'>169</span>",
                "language": "en"
            },
            "on": {
                "full": "https://readux.io/iiif/v2/7c17c670-d723-4c41-b8fe-61ba56938604/canvas/7c17c670-d723-4c41-b8fe-61ba56938604_11194-P0085-I0000-P0000-BP.jpg",
                "@type": "oa:SpecificResource",
                "within": {
                    "@id": "https://readux.io/iiif/v2/7c17c670-d723-4c41-b8fe-61ba56938604/manifest",
                    "@type": "sc:Manifest"
                },
                "selector": {
                    "@type": "oa:FragmentSelector",
                    "value": "xywh=2914,2812,58,32",
                    "item": {
                        "@type": "oa:FragmentSelector"
                    }
                }
            },
            "stylesheet": {
                "type": "CssStylesheet",
                "value": ".anno-e033742b-97d4-4915-bf29-61dbf6199af8: { height: 32px; width: 58px; font-size: 20.0px; letter-spacing: 9.333333333333334px;}"
            }
        }
    ]
}